{
  "company": "Render",
  "slug": "render-interview-guide",
  "url": "https://www.techinterview.org/companies/render-interview-guide",
  "scrapedAt": "2026-07-02T07:25:42.380Z",
  "interviewStages": [
    "Behavioral: ownership, customer empathy, working in small teams"
  ],
  "codingTopics": [
    "Practical systems coding: parsers, queues, small state machines",
    "Streaming and time-series: windowed aggregation over log and metric events",
    "String parsing: query languages, config formats",
    "Data structures: ring buffers, LRU caches, tries",
    "Graph and topological: build and dependency ordering"
  ],
  "systemDesignTopics": [
    "Design a managed Postgres service with point-in-time recovery and read replicas",
    "Design a build pipeline that deploys from git push to running container",
    "Design log streaming from thousands of customer applications to a queryable backend"
  ],
  "behavioralTopics": [],
  "sampleQuestions": {
    "coding": [
      "At Render, parse a stream of log and metric events and aggregate by key over a sliding window. Discuss memory bounds.",
      "Implement a rate-limited, back-pressured queue for ingestion. Discuss what happens when a downstream sink is slow.",
      "Parse a config format into a typed structure with schema validation. Discuss error handling.",
      "Given a dependency graph of build targets, compute a valid build order and detect cycles via topological sort.",
      "Downsample a time-series into fixed buckets (min, max, avg) as data streams in. Walk through the approach."
    ],
    "behavioral": [
      "Tell me about a project you are proud of at Render scale and the hardest tradeoff you made.",
      "Give me an example that shows ownership, customer empathy, working in small teams.",
      "Describe a time you disagreed with a teammate or manager. How did it resolve?",
      "Tell me about a time you took ownership of an ambiguous problem end to end."
    ],
    "systemDesign": [
      "Design a managed Postgres service with point-in-time recovery and read replicas.",
      "Design a build pipeline that deploys from git push to running container.",
      "Design log streaming from thousands of customer applications to a queryable backend."
    ],
    "values": [
      "Render is trusted by the developers who depend on it. Describe a time you prioritized reliability and craft.",
      "Tell me about an open-source contribution or public work you are proud of.",
      "How do you weigh a breaking change against the migration cost for users?"
    ],
    "other": [
      "Is Render hiring aggressively?",
      "How does Render compare to Vercel or Railway?",
      "What stack does Render use?"
    ]
  },
  "difficulty": 7,
  "tips": [],
  "compensation": null,
  "rawSummary": "Render Interview Guide (2026): Cloud Platform Engineering\nBy \t\t\t\n\t\t\t\t\n\t\t\t\ttechinterview.org\t\t\t\n\t\t\t\n\t\t\n\n\t\t /  May 5, 2026 \n\t\t\t\n\t\t\n\n\t\n\t\n\t\n\n\t\t\n\t\t\nOn this page\n\n- Process\n\n- What they actually ask\n\n- Levels and comp (2026)\n\n- Prep priorities\n\n- Frequently Asked Questions\n\nUpdated May 5, 2026 · techinterview.org\n\n⏱ 1 min read\n\nRender\nrender.com ↗\n\nRender is the modern alternative to Heroku — git-push deploys, managed databases, simple pricing, and a developer experience tuned for indie hackers and growing startups. The interview is small-team practical and rewards generalists who can ship across the stack.\n\nProcess\n\nRecruiter screen → 60-minute technical phone (DSA + practical question) → onsite virtual: 1 coding pair, 1 system design, 1 past-project deep dive, 1 behavioral. Cycle: 2–4 weeks. Render hires deliberately — small team, high bar.\n\nWhat they actually ask\n\n- Design a managed Postgres service with point-in-time recovery and read replicas\n\n- Design a build pipeline that deploys from git push to running container\n\n- Design log streaming from thousands of customer applications to a queryable backend\n\n- Coding: practical refactors or feature additions, often in Go or TypeScript\n\n- Behavioral: ownership, customer empathy, working in small teams\n\nLevels and comp (2026)\n\n- SE: $180K–$240K total\n\n- Senior SE: $260K–$340K\n\n- Staff: $360K–$470K\n\n- Principal: $480K–$620K\n\nPrep priorities\n\n- Be fluent with Kubernetes, container orchestration, and PaaS architectural patterns\n\n- Know your way around Postgres, Redis, and managed-database operational concerns\n\n- Demonstrate startup hustle — Render values shippers\n\nFrequently Asked Questions\n\nIs Render hiring aggressively?\n\nSelective and growing. Engineering team is in the low hundreds. Most roles are SF-hybrid or remote within US.\n\nHow does Render compare to Vercel or Railway?\n\nRender is broader (full PaaS + databases) than Vercel (frontend-first). Comparable scope to Railway with a more mature operational track record.\n\nWhat stack does Render use?\n\nGo for the core platform, TypeScript for frontend/dashboard, Kubernetes for orchestration.\n\nSimilar company guides\n\nChronosphereinterview guideDopplerinterview guideReka AIinterview guideSakana AIinterview guideDuckDB Labsinterview guideSingleStoreinterview guide\n\nPrepping for Render? Put it to work:\nBuild a study planCheck your resumeCalculate the offerUp nextSearch Autocomplete System Low-Level Design⏱ 9 min readShard Rebalancing Low-Level Design: Split/Merge Triggers, Data Migration, and Minimal Downtime⏱ 8 min readLow Level Design: Memory Allocator Design⏱ 3 min read"
}
