{
  "company": "SingleStore",
  "slug": "singlestore-interview-guide",
  "url": "https://www.techinterview.org/companies/singlestore-interview-guide",
  "scrapedAt": "2026-07-02T07:26:19.192Z",
  "interviewStages": [
    "Behavioral: ownership, deep technical taste, distributed-systems craft"
  ],
  "codingTopics": [],
  "systemDesignTopics": [],
  "behavioralTopics": [],
  "sampleQuestions": {
    "coding": [
      "Given an array of integers, find the two numbers that add up to a target value. Talk through your approach, complexity, and edge cases.",
      "Given a string, find the length of the longest substring without repeating characters. Walk through your solution.",
      "Design a data structure that supports insert, delete, and get-random in constant time. Explain your reasoning."
    ],
    "behavioral": [
      "Tell me about a time you disagreed with a teammate or manager. How did it resolve?",
      "Describe a project that failed or fell short. What did you learn and change afterward?",
      "Give me an example of when you took ownership of something outside your job description."
    ],
    "systemDesign": [],
    "values": [],
    "other": [
      "Is SingleStore remote-friendly?",
      "How does SingleStore compare to Snowflake, ClickHouse, or CockroachDB?",
      "What is the engineering culture?"
    ]
  },
  "difficulty": null,
  "tips": [],
  "compensation": null,
  "rawSummary": "SingleStore Interview Guide (2026): Real-Time Analytical Database\nBy \t\t\t\n\t\t\t\t\n\t\t\t\ttechinterview.org\t\t\t\n\t\t\t\n\t\t\n\n\t\t /  May 6, 2026 \n\t\t\t\n\t\t\n\n\t\n\t\n\t\n\n\t\t\n\t\t\nOn this page\n\n- Process\n\n- What they actually ask\n\n- Levels and comp (2026)\n\n- Prep priorities\n\n- Frequently Asked Questions\n\nUpdated May 6, 2026 · techinterview.org\n\n⏱ 1 min read\n\nSingleStore\nsinglestore.com ↗\n\nSingleStore (formerly MemSQL) is a real-time HTAP database — combines transactional and analytical workloads in a distributed, columnar-and-rowstore engine. Late-stage. The interview emphasizes deep distributed-database systems work, query optimization, and the unique architectural tradeoffs of an HTAP system.\n\nProcess\n\nRecruiter screen → 60-minute coding (C++ or Go for engine roles, Python for tools) → onsite virtual: 2 coding, 1 system design (distributed-systems-flavored), 1 craft deep-dive, 1 behavioral. Cycle: 4–6 weeks.\n\nWhat they actually ask\n\n- Design a sharded distributed SQL engine with rowstore and columnstore\n\n- Design a query optimizer that picks across storage formats\n\n- Design a real-time ingestion pipeline (Kafka → SingleStore)\n\n- Coding: medium-hard DSA, often with concurrency or systems framing\n\n- Behavioral: ownership, deep technical taste, distributed-systems craft\n\nLevels and comp (2026)\n\n- SE: $175K–$235K total\n\n- Senior SE: $250K–$345K total\n\n- Staff: $360K–$485K total\n\n- Principal: $495K–$670K total\n\nPrep priorities\n\n- Be fluent in C++ (the engine) and SQL deeply\n\n- Understand distributed query execution, sharding, replication (Raft)\n\n- Brush up on columnar storage, vectorized execution, and query optimization\n\nFrequently Asked Questions\n\nIs SingleStore remote-friendly?\n\nHubs in San Francisco (HQ), Seattle, Portugal, India. Many engineering roles fully remote within supported geographies.\n\nHow does SingleStore compare to Snowflake, ClickHouse, or CockroachDB?\n\nSnowflake is analytical-only at scale. ClickHouse is open-source columnar-focused. Cockroach is OLTP-focused distributed SQL. SingleStore differentiates on HTAP — real-time read+write at scale. Comp competitive for senior+ database systems work.\n\nWhat is the engineering culture?\n\nSenior-heavy, technically deep, calmer pace. Strong distributed-systems craft.\n\nSimilar company guides\n\nChronosphereinterview guideDopplerinterview guideReka AIinterview guideSakana AIinterview guideDuckDB Labsinterview guideOrca Securityinterview guide\n\nPrepping for SingleStore? Put it to work:\nBuild a study planCheck your resumeCalculate the offerUp nextPlaid Interview Guide 2026: Financial Data Infrastructure, Idempotency, and Bank API Engineering⏱ 9 min readHackerRank Interview Guide (2026): Coding Assessment Platform⏱ 1 min readCount Negative Numbers in a Sorted Matrix: Staircase Search⏱ 5 min read"
}
